ml_pipelines_framework/__init__.py
ml_pipelines_framework/batch_inference_tabular/__init__.py
ml_pipelines_framework/batch_inference_tabular/__main__.py
ml_pipelines_framework/data_loader/__init__.py
ml_pipelines_framework/data_loader/__main__.py
ml_pipelines_framework/deploy_online_serving/__init__.py
ml_pipelines_framework/deploy_online_serving/__main__.py
ml_pipelines_framework/feature_preparation/__init__.py
ml_pipelines_framework/feature_preparation/__main__.py
ml_pipelines_framework/release/__init__.py
ml_pipelines_framework/release/__main__.py
ml_pipelines_framework/test_online_inference/__init__.py
ml_pipelines_framework/test_online_inference/__main__.py
ml_pipelines_framework/trainer/__init__.py
ml_pipelines_framework/trainer/__main__.py
epamml_pipelines_framework-0.5.1.dist-info/METADATA
epamml_pipelines_framework-0.5.1.dist-info/WHEEL
epamml_pipelines_framework-0.5.1.dist-info/entry_points.txt
epamml_pipelines_framework-0.5.1.dist-info/top_level.txt
epamml_pipelines_framework-0.5.1.dist-info/RECORD
